zetacore-0.1.0.dist-info/METADATA
zetacore-0.1.0.dist-info/WHEEL
zetacore-0.1.0.dist-info/licenses/LICENSE
zetacore/__init__.py
zetacore/zetacore.cpython-312-darwin.so
zetacore-0.1.0.dist-info/RECORD
