Metadata-Version: 2.3
Name: zetacore
Version: 0.1.0
Classifier: Programming Language :: Rust
Classifier: Programming Language :: Python :: Implementation :: CPython
Classifier: Programming Language :: Python :: Implementation :: PyPy
License-File: LICENSE
Summary: A simple in-memory vector store library.
Keywords: LLM,vector-store,similarity-search,python-bindings
Author: zenithvrx
License: Apache-2.0
Requires-Python: >=3.7
